wtf_transcript_converter/__init__.py
wtf_transcript_converter/exceptions.py
wtf_transcript_converter/cli/__init__.py
wtf_transcript_converter/cli/cross_provider.py
wtf_transcript_converter/cli/main.py
wtf_transcript_converter/core/__init__.py
wtf_transcript_converter/core/converter.py
wtf_transcript_converter/core/models.py
wtf_transcript_converter/core/validator.py
wtf_transcript_converter/cross_provider/__init__.py
wtf_transcript_converter/cross_provider/consistency.py
wtf_transcript_converter/cross_provider/performance.py
wtf_transcript_converter/cross_provider/quality.py
wtf_transcript_converter/providers/__init__.py
wtf_transcript_converter/providers/assemblyai.py
wtf_transcript_converter/providers/base.py
wtf_transcript_converter/providers/canary.py
wtf_transcript_converter/providers/deepgram.py
wtf_transcript_converter/providers/parakeet.py
wtf_transcript_converter/providers/rev_ai.py
wtf_transcript_converter/providers/whisper.py
wtf_transcript_converter/utils/__init__.py
wtf_transcript_converter/utils/confidence_utils.py
wtf_transcript_converter/utils/language_utils.py
wtf_transcript_converter/utils/time_utils.py
vcon_wtf-0.1.1.dist-info/METADATA
vcon_wtf-0.1.1.dist-info/WHEEL
vcon_wtf-0.1.1.dist-info/entry_points.txt
vcon_wtf-0.1.1.dist-info/licenses/LICENSE
vcon_wtf-0.1.1.dist-info/RECORD
