Metadata-Version: 2.4
Name: vcon-wtf
Version: 0.1.1
Summary: Convert transcript JSONs to/from IETF World Transcription Format (WTF)
Project-URL: Homepage, https://github.com/vcon-dev/wtf-transcript-converter
Project-URL: Repository, https://github.com/vcon-dev/wtf-transcript-converter
Project-URL: Documentation, https://vcon-wtf.readthedocs.io
Project-URL: Bug Tracker, https://github.com/vcon-dev/wtf-transcript-converter/issues
Author-email: vCon Development Team <vcon@ietf.org>
License: MIT License
License-File: LICENSE
Classifier: Development Status :: 3 - Alpha
Classifier: Intended Audience :: Developers
Classifier: License :: OSI Approved :: MIT License
Classifier: Programming Language :: Python :: 3
Classifier: Programming Language :: Python :: 3.12
Classifier: Topic :: Multimedia :: Sound/Audio :: Speech
Classifier: Topic :: Text Processing :: Markup
Requires-Python: >=3.12
Requires-Dist: click>=8.0.0
Requires-Dist: jsonschema>=4.0.0
Requires-Dist: pydantic>=2.0.0
Requires-Dist: pytest-cov>=7.0.0
Requires-Dist: pytest-mock>=3.15.1
Requires-Dist: pytest>=8.4.2
Requires-Dist: python-dateutil>=2.8.0
Requires-Dist: rich>=13.0.0
Requires-Dist: twine>=6.2.0
Provides-Extra: dev
Requires-Dist: bandit>=1.7.0; extra == 'dev'
Requires-Dist: black>=24.0.0; extra == 'dev'
Requires-Dist: flake8-bugbear>=23.0.0; extra == 'dev'
Requires-Dist: flake8-docstrings>=1.7.0; extra == 'dev'
Requires-Dist: flake8>=6.0.0; extra == 'dev'
Requires-Dist: isort>=5.12.0; extra == 'dev'
Requires-Dist: mypy>=1.0.0; extra == 'dev'
Requires-Dist: pre-commit>=3.0.0; extra == 'dev'
Requires-Dist: pytest-cov>=4.0.0; extra == 'dev'
Requires-Dist: pytest-mock>=3.10.0; extra == 'dev'
Requires-Dist: pytest>=7.0.0; extra == 'dev'
Requires-Dist: safety>=2.3.0; extra == 'dev'
Provides-Extra: test
Requires-Dist: pytest-cov>=4.0.0; extra == 'test'
Requires-Dist: pytest-mock>=3.10.0; extra == 'test'
Requires-Dist: pytest>=7.0.0; extra == 'test'
